LICENSE
README.md
setup.py
rhparse/__init__.py
rhparse/rhparse.py
rhparse.egg-info/PKG-INFO
rhparse.egg-info/SOURCES.txt
rhparse.egg-info/dependency_links.txt
rhparse.egg-info/requires.txt
rhparse.egg-info/top_level.txt